odoo/addons/fieldservice_portal/README.rst
odoo/addons/fieldservice_portal/__init__.py
odoo/addons/fieldservice_portal/__manifest__.py
odoo/addons/fieldservice_portal/controllers/__init__.py
odoo/addons/fieldservice_portal/controllers/fsm_order_portal.py
odoo/addons/fieldservice_portal/demo/fsm_location_demo.xml
odoo/addons/fieldservice_portal/demo/fsm_order_demo.xml
odoo/addons/fieldservice_portal/i18n/ca.po
odoo/addons/fieldservice_portal/i18n/es.po
odoo/addons/fieldservice_portal/i18n/fieldservice_portal.pot
odoo/addons/fieldservice_portal/i18n/it.po
odoo/addons/fieldservice_portal/i18n/pt_BR.po
odoo/addons/fieldservice_portal/i18n/sv.po
odoo/addons/fieldservice_portal/models/__init__.py
odoo/addons/fieldservice_portal/models/fsm_stage.py
odoo/addons/fieldservice_portal/readme/CONFIGURE.md
odoo/addons/fieldservice_portal/readme/CONTRIBUTORS.md
odoo/addons/fieldservice_portal/readme/DESCRIPTION.md
odoo/addons/fieldservice_portal/security/ir.model.access.csv
odoo/addons/fieldservice_portal/security/portal_security.xml
odoo/addons/fieldservice_portal/static/description/icon.png
odoo/addons/fieldservice_portal/static/description/index.html
odoo/addons/fieldservice_portal/static/src/img/fsmorder.svg
odoo/addons/fieldservice_portal/static/src/js/fsm_order_portal.esm.js
odoo/addons/fieldservice_portal/tests/__init__.py
odoo/addons/fieldservice_portal/tests/test_portal.py
odoo/addons/fieldservice_portal/views/fsm_order_template.xml
odoo/addons/fieldservice_portal/views/fsm_stage.xml
odoo/addons/fieldservice_portal/views/portal_template.xml
odoo_addon_fieldservice_portal-18.0.1.0.0.4.dist-info/METADATA
odoo_addon_fieldservice_portal-18.0.1.0.0.4.dist-info/WHEEL
odoo_addon_fieldservice_portal-18.0.1.0.0.4.dist-info/top_level.txt
odoo_addon_fieldservice_portal-18.0.1.0.0.4.dist-info/RECORD
